bytedbytegraph_consumer/__init__.py
bytedbytegraph_consumer-0.0.1.dist-info/METADATA
bytedbytegraph_consumer-0.0.1.dist-info/WHEEL
bytedbytegraph_consumer-0.0.1.dist-info/top_level.txt
bytedbytegraph_consumer-0.0.1.dist-info/RECORD
