Metadata-Version: 2.1
Name: bytedbytegraph-consumer
Version: 0.0.1
Summary: A simple package named bytedbytegraph_consumer
Home-page: https://github.com/artifact/bytedbytegraph_consumer.git
Author: artifact
Author-email: artifact@example.com
License: UNKNOWN
Platform: UNKNOWN
Classifier: Programming Language :: Python :: 3
Classifier: License :: OSI Approved :: MIT License
Classifier: Operating System :: OS Independent
